l0n0ltcp/ChaCha20.py
l0n0ltcp/SOCKS5服务器.py
l0n0ltcp/TCP转发任务.py
l0n0ltcp/TCP转发客户端.py
l0n0ltcp/TCP转发服务器.py
l0n0ltcp/__init__.py
l0n0ltcp/心跳.py
l0n0ltcp/消息.py
l0n0ltcp/通用.py
l0n0ltcp-2.0.3.dist-info/METADATA
l0n0ltcp-2.0.3.dist-info/WHEEL
l0n0ltcp-2.0.3.dist-info/entry_points.txt
l0n0ltcp-2.0.3.dist-info/top_level.txt
l0n0ltcp-2.0.3.dist-info/RECORD
