Metadata-Version: 2.1
Name: l0n0ltcp
Version: 2.0.3
Summary: TCP转发服务器
Requires-Python: >=3.8
Requires-Dist: pymonocypher
